progress_tracker/__init__.py
progress_tracker/progress_tracker.py
progress_tracker/py.typed
progress_tracker/timeout.py
progress_tracker-1.0.0.dist-info/METADATA
progress_tracker-1.0.0.dist-info/RECORD
progress_tracker-1.0.0.dist-info/WHEEL
progress_tracker-1.0.0.dist-info/top_level.txt
