Metadata-Version: 2.1
Name: progress-tracker
Version: 1.0.0
Summary: A utility that wraps an Iterable and regularly prints out progress on the processing of that Iterable
Home-page: UNKNOWN
Author: exactEarth Ltd.
Author-email: open-source@exactearth.com
License: MIT
Platform: UNKNOWN
Classifier: Intended Audience :: Developers
Classifier: License :: OSI Approved :: MIT License
Classifier: Operating System :: OS Independent
Classifier: Programming Language :: Python
Classifier: Programming Language :: Python :: 3
Classifier: Programming Language :: Python :: 3.6
Classifier: Programming Language :: Python :: 3.7
Classifier: Topic :: Software Development :: Libraries :: Python Modules
Requires-Python: >=3.6
